pychoco/__init__.py
pychoco/_backend.cp313-win_amd64.pyd
pychoco/_handle_wrapper.py
pychoco/_utils.py
pychoco/backend.py
pychoco/choco_capi.dll
pychoco/libchoco_capi.dll
pychoco/model.py
pychoco/parallel_portfolio.py
pychoco/py.typed
pychoco/solution.py
pychoco/solver.py
pychoco/utils.py
pychoco/constraints/__init__.py
pychoco/constraints/constraint.py
pychoco/constraints/graph_constraint_factory.py
pychoco/constraints/int_constraint_factory.py
pychoco/constraints/reification_factory.py
pychoco/constraints/sat_factory.py
pychoco/constraints/set_constraint_factory.py
pychoco/constraints/cnf/__init__.py
pychoco/constraints/cnf/log_op.py
pychoco/constraints/extension/__init__.py
pychoco/constraints/extension/hybrid/__init__.py
pychoco/constraints/extension/hybrid/supportable.py
pychoco/objects/__init__.py
pychoco/objects/automaton/__init__.py
pychoco/objects/automaton/cost_automaton.py
pychoco/objects/automaton/finite_automaton.py
pychoco/objects/graphs/__init__.py
pychoco/objects/graphs/directed_graph.py
pychoco/objects/graphs/graph.py
pychoco/objects/graphs/multivalued_decision_diagram.py
pychoco/objects/graphs/undirected_graph.py
pychoco/search/__init__.py
pychoco/search/search_strategies.py
pychoco/variables/__init__.py
pychoco/variables/boolvar.py
pychoco/variables/directed_graphvar.py
pychoco/variables/graphvar.py
pychoco/variables/intvar.py
pychoco/variables/setvar.py
pychoco/variables/task.py
pychoco/variables/undirected_graphvar.py
pychoco/variables/variable.py
pychoco/variables/variable_factory.py
pychoco/variables/view_factory.py
pychoco-0.2.6.dist-info/licenses/LICENSE
tests/__init__.py
tests/test_boolvar.py
tests/test_graph.py
tests/test_graphvar.py
tests/test_intvars.py
tests/test_mdd.py
tests/test_model.py
tests/test_parallel_portfolio.py
tests/test_search_strategies.py
tests/test_setvar.py
tests/test_solver.py
tests/test_task.py
tests/test_views.py
tests/graph_constraints/__init__.py
tests/graph_constraints/test_graph_anti_symmetric.py
tests/graph_constraints/test_graph_biconnected.py
pychoco-0.2.6.dist-info/METADATA
pychoco-0.2.6.dist-info/WHEEL
pychoco-0.2.6.dist-info/top_level.txt
pychoco-0.2.6.dist-info/RECORD
